wikipedia_mcp/__init__.py
wikipedia_mcp/__main__.py
wikipedia_mcp/parser.py
wikipedia_mcp/server.py
wikipedia_mcp/types.py
wikipedia_mcp_server-1.0.1.dist-info/licenses/LICENSE
wikipedia_mcp_server-1.0.1.dist-info/METADATA
wikipedia_mcp_server-1.0.1.dist-info/WHEEL
wikipedia_mcp_server-1.0.1.dist-info/entry_points.txt
wikipedia_mcp_server-1.0.1.dist-info/top_level.txt
wikipedia_mcp_server-1.0.1.dist-info/RECORD
