Metadata-Version: 2.4
Name: wikipedia-mcp-server
Version: 1.0.1
Summary: A Model Context Protocol server providing tools for querying Wikipedia for LLMs.
Author-email: Yang Sheng Han <progamesigner@gmail.com>
License: MIT
Keywords: wikipedia,mcp,llm
Classifier: Development Status :: 4 - Beta
Classifier: Framework :: AsyncIO
Classifier: Framework :: Pydantic
Classifier: Framework :: Pydantic :: 2
Classifier: Intended Audience :: Developers
Classifier: License :: OSI Approved :: MIT License
Classifier: Programming Language :: Python :: 3.13
Classifier: Programming Language :: Python :: 3
Requires-Python: >=3.13
License-File: LICENSE
Requires-Dist: fastmcp>=2.9.0
Requires-Dist: httpx>=0.28.1
Requires-Dist: pydantic>=2.11.7
Requires-Dist: pydantic-settings>=2.10.0
Dynamic: license-file
